tstickers/__init__.py
tstickers/__main__.py
tstickers/caching.py
tstickers/cli.py
tstickers/convert.py
tstickers/convert_pyrlottie.py
tstickers/convert_rlottie_python.py
tstickers/downloader.py
tstickers-2024.1.3.dist-info/entry_points.txt
tstickers-2024.1.3.dist-info/LICENSE.md
tstickers-2024.1.3.dist-info/METADATA
tstickers-2024.1.3.dist-info/WHEEL
tstickers-2024.1.3.dist-info/RECORD
