Metadata-Version: 2.1
Name: tstickers
Version: 2024.1.3
Summary: Download sticker packs from Telegram
Home-page: https://github.com/FHPythonUtils/TStickers
License: MIT
Author: FredHappyface
Requires-Python: >=3.9,<4.0
Classifier: Development Status :: 5 - Production/Stable
Classifier: Intended Audience :: Developers
Classifier: Intended Audience :: Education
Classifier: License :: OSI Approved :: MIT License
Classifier: Natural Language :: English
Classifier: Operating System :: OS Independent
Classifier: Programming Language :: Python :: 3
Classifier: Programming Language :: Python :: 3.9
Classifier: Programming Language :: Python :: 3.10
Classifier: Programming Language :: Python :: 3.11
Classifier: Programming Language :: Python :: 3.12
Classifier: Programming Language :: Python :: Implementation :: CPython
Classifier: Topic :: Multimedia :: Graphics
Classifier: Topic :: Software Development :: Libraries :: Python Modules
Classifier: Topic :: Utilities
Provides-Extra: pyrlottie
Provides-Extra: rlottie-python
Requires-Dist: Pillow (>=10.4.0,<11)
Requires-Dist: emoji (>=2.12.1,<3)
Requires-Dist: loguru (>=0.7.2,<2)
Requires-Dist: pyrlottie (>=2024.0.1,<2026) ; extra == "pyrlottie"
Requires-Dist: requests (>=2.32.3,<3)
Requires-Dist: requests-cache (>=1.2.1,<2)
Requires-Dist: rlottie-python (>=1.3.6,<2) ; extra == "rlottie-python"
Project-URL: Documentation, https://github.com/FHPythonUtils/TStickers/blob/master/README.md
Project-URL: Repository, https://github.com/FHPythonUtils/TStickers
